xontrib/__init__.py
xontrib/common_fate_granted.xsh
xontrib_common_fate_granted-0.0.1.dist-info/LICENSE
xontrib_common_fate_granted-0.0.1.dist-info/METADATA
xontrib_common_fate_granted-0.0.1.dist-info/WHEEL
xontrib_common_fate_granted-0.0.1.dist-info/top_level.txt
xontrib_common_fate_granted-0.0.1.dist-info/RECORD
