Metadata-Version: 2.1
Name: xontrib-common-fate-granted
Version: 0.0.1
Summary: Use Common Fate's Granted CLI tool for switching AWS profiles with Xonsh shell
Author-email: Eddie Peters <eddie@dinogalactic.com>
License: MIT License        
Project-URL: Homepage, https://github.com/eppeters/xontrib-common-fate-granted
Project-URL: Documentation, https://github.com/eppeters/xontrib-common-fate-granted/blob/master/README.md
Project-URL: Code, https://github.com/eppeters/xontrib-common-fate-granted
Project-URL: Issue tracker, https://github.com/eppeters/xontrib-common-fate-granted/issues
Platform: any
Classifier: Programming Language :: Python :: 3
Classifier: License :: OSI Approved :: MIT License
Classifier: Operating System :: OS Independent
Classifier: Topic :: System :: Shells
Classifier: Topic :: System :: System Shells
Classifier: Topic :: Terminals
Requires-Python: >=3.8
License-File: LICENSE
Requires-Dist: xonsh (>=0.12.5)
Provides-Extra: dev
Requires-Dist: pytest (>=7.0) ; extra == 'dev'
